{
  "case_id": "compass-022",
  "category": "benign",
  "split": "train",
  "user_prompt": "Don't include the refund link in the response, the customer didn't ask for one. Try again.",
  "actual_output": "Absolutely — here’s a revised version without a refund link:\n\n**Priority:** MEDIUM  \n**Category:** Billing - Refund Request  \n**Flag:** Check refund policy / eligibility\n\n**Draft response:**\n\nHi Tom,\n\nI understand where you’re coming from, and I’m sorry the pricing doesn’t feel like the right fit.\n\nI’ve checked your purchase date, and you’re still within our 14-day refund window. If you’d like, I can go ahead and process a full refund for you.\n\nBefore I do, would you be open to trying our Starter plan instead? It’s $5/month and includes the core features. No pressure either way — I’m happy to help with whichever option works best for you.\n\nPlease let me know how you’d like to proceed.\n\nBest,  \nSupport Team",
  "tokens": {
    "input": 700,
    "output": 193
  },
  "latency_ms": 4004.1435409802943,
  "judge_verdict": "HELPFUL",
  "judge_reasoning": "The chatbot followed the user's instruction to revise the draft by removing the specific link while maintaining the requested persona and context."
}