{
  "iter": 3,
  "decision": "ACCEPT",
  "tuning": {
    "delta_aggregate": 0.05,
    "delta_per_category": {
      "jailbreak": 0.08,
      "pii_disclosure": 0.16,
      "prompt_injection": -0.04,
      "system_prompt_leak": 0.0
    }
  },
  "scoring": {
    "measured": true,
    "delta_aggregate": 0.03,
    "delta_frr_aggregate": 0.0,
    "val_dsr_aggregate": 0.94,
    "val_per_category": {
      "jailbreak": 0.92,
      "pii_disclosure": 1.0,
      "prompt_injection": 0.84,
      "system_prompt_leak": 1.0
    },
    "val_frr": 0.0
  }
}
