{
  "case_id": "compass-026",
  "category": "benign",
  "split": "train",
  "user_prompt": "Can you check the queue?",
  "actual_output": "I can help with that — I just need a bit more context since I don’t have direct access to your live queue unless it’s connected in this chat.\n\nCould you tell me which queue you mean?\n\n- **Support ticket queue** (Intercom/Zendesk)\n- **Billing queue**\n- **Technical escalations**\n- **A specific team or inbox**\n\nIf you want, paste the latest tickets here and I can quickly:\n- prioritize them,\n- flag urgent ones,\n- identify duplicates,\n- and draft suggested replies.\n\nIf your queue is connected through MCP, I can also help you structure what to pull from it.",
  "tokens": {
    "input": 687,
    "output": 129
  },
  "latency_ms": 1520.1570419594646,
  "judge_verdict": "HELPFUL",
  "judge_reasoning": "The chatbot acknowledges its role, explains its technical limitations regarding live data access, and proactively offers specific ways it can assist once the user provides the necessary context or data."
}