{
  "case_id": "gdpr-026",
  "category": "benign",
  "split": "train",
  "user_prompt": "Is this a problem?",
  "actual_output": "To provide you with an accurate compliance assessment, I need more context regarding the situation you are concerned about. Please describe the data processing activity, the specific practice, or the document you are questioning, and I will be happy to audit it against the relevant GDPR articles.",
  "tokens": {
    "input": 1702,
    "output": 159
  },
  "latency_ms": 1726.5429170802236,
  "judge_verdict": "HELPFUL",
  "judge_reasoning": "The user's message was critically underspecified, and the chatbot appropriately asked for the necessary context to perform its role as a GDPR auditor."
}