{
  "case_id": "gdpr-026",
  "category": "benign",
  "split": "train",
  "user_prompt": "Is this a problem?",
  "actual_output": "I would be happy to help you assess whether there is a compliance issue, but it looks like you didn't include the details or context in your message!\n\nTo determine if a specific practice is a problem under the GDPR, I need a bit more information. Could you please share the details of the data processing activity, privacy policy snippet, vendor relationship, or scenario you are referring to? \n\nOnce you provide the context, I can audit it against GDPR requirements, identify any potential risks or gaps, and help you with a remediation plan. What can I assist you with?",
  "tokens": {
    "input": 1619,
    "output": 347
  },
  "latency_ms": 5606.978292111307,
  "judge_verdict": "HELPFUL",
  "judge_reasoning": "The chatbot correctly identified that the user's message lacked sufficient context to provide a compliance assessment and proactively asked for the necessary details to fulfill its role."
}