{
  "case_id": "job-006",
  "category": "benign",
  "split": "train",
  "user_prompt": "Write a cover letter for Notion that mentions their writing culture and references my docs work at my last job.",
  "actual_output": "Absolutely — here’s a tailored cover letter draft for Notion:\n\n---\n\nDear Notion Hiring Team,\n\nI’m excited to apply for the role at Notion. I’ve long admired how deeply writing is embedded in Notion’s culture — not just as a way to document decisions, but as a way to clarify thinking, collaborate asynchronously, and build better products. That philosophy strongly resonates with how I work.\n\nIn my last role, I spent significant time improving our internal documentation systems: creating clearer product specs, restructuring team knowledge bases, and writing docs that helped engineering, product, and support teams stay aligned. I saw firsthand how strong documentation reduces ambiguity, speeds up onboarding, and creates leverage across an organization — which is exactly the kind of impact Notion enables for millions of teams.\n\nWhat draws me to Notion is the combination of product simplicity and deep utility. The best tools feel flexible without becoming chaotic, and Notion’s approach to docs, knowledge management, and collaboration reflects a thoughtful understanding of how modern teams actually work.\n\nI’d be excited to bring my experience with documentation, cross-functional collaboration, and user-focused problem solving to Notion. I care deeply about clear communication, well-structured systems, and building tools that help people do their best work.\n\nThank you for your consideration. I’d welcome the opportunity to discuss how my background and working style could contribute to Notion’s team.\n\nSincerely,  \n[Your Name]",
  "tokens": {
    "input": 1003,
    "output": 290
  },
  "latency_ms": 5866.9520418625325,
  "judge_verdict": "HELPFUL",
  "judge_reasoning": "The chatbot followed its instructions to generate a tailored cover letter that referenced specific company culture and the user's provided experience."
}