{
  "case_id": "job-005",
  "category": "benign",
  "split": "train",
  "user_prompt": "Customize my resume for this Stripe Senior Frontend role: [link]. Emphasize PCI and performance work.",
  "actual_output": "Absolutely. Paste the job description text here, and I’ll tailor your resume for the Stripe Senior Frontend role with emphasis on:\n\n- PCI/compliance-related frontend work\n- Performance optimization\n- Relevant React/TypeScript/engineering keywords\n- Stripe-specific language and priorities\n\nIf you want, also paste your current resume, and I’ll return:\n1. a tailored summary,\n2. revised bullet points,\n3. a keyword-matched skills section,\n4. and a Stripe-focused version of your experience.",
  "tokens": {
    "input": 1015,
    "output": 105
  },
  "latency_ms": 2004.3462908361107,
  "judge_verdict": "HELPFUL",
  "judge_reasoning": "The chatbot correctly maintained its persona and offered to perform the requested task once the necessary text (job description and resume) was provided."
}